{
   "Sentences": [
      {
         "SentenceId": 0,
         "Tokens": [
            "Sehr",
            "geehrte",
            "Frau",
            "Präsidentin",
            "!"
         ]
      },
      {
         "SentenceId": 1,
         "Tokens": [
            "Meine",
            "sehr",
            "verehrten",
            "Damen",
            "und",
            "Herren",
            "!"
         ]
      },
      {
         "SentenceId": 2,
         "Tokens": [
            "Die",
            "Relevanz",
            "dieses",
            "Themas",
            "ist",
            ",",
            "denke",
            "ich",
            ",",
            "allen",
            "klar",
            "."
         ]
      },
      {
         "SentenceId": 3,
         "Tokens": [
            "Ich",
            "schränke",
            "diese",
            "Aussage",
            "ein",
            ":"
         ]
      },
      {
         "SentenceId": 4,
         "Tokens": [
            "Es",
            "gab",
            "in",
            "dieser",
            "Debatte",
            "Redner",
            ",",
            "die",
            "das",
            "noch",
            "nicht",
            "verstanden",
            "haben",
            ",",
            "die",
            "hier",
            "den",
            "Trump",
            "gemacht",
            "haben",
            "."
         ]
      },
      {
         "SentenceId": 5,
         "Tokens": [
            "Ich",
            "denke",
            ",",
            "zu",
            "allen",
            "Themenfeldern",
            ",",
            "die",
            "hier",
            "angesprochen",
            "worden",
            "sind",
            ",",
            "haben",
            "wir",
            "in",
            "diesem",
            "Hause",
            "viele",
            "Diskussionen",
            "über",
            "den",
            "richtigen",
            "Weg",
            "geführt",
            "."
         ]
      },
      {
         "SentenceId": 6,
         "Tokens": [
            "Jedem",
            "ist",
            "klar",
            ",",
            "dass",
            "Deutschland",
            "eine",
            "besondere",
            "Verantwortung",
            "trägt",
            "und",
            "einen",
            "Beitrag",
            "dazu",
            "leisten",
            "muss",
            ",",
            "dass",
            "die",
            "Klimaziele",
            "erreicht",
            "werden",
            "."
         ]
      },
      {
         "SentenceId": 7,
         "Tokens": [
            "Dieser",
            "Antrag",
            "trägt",
            "dazu",
            "bei",
            ",",
            "dieses",
            "Thema",
            "hier",
            "noch",
            "einmal",
            "auf",
            "die",
            "Tagesordnung",
            "zu",
            "bringen",
            "."
         ]
      },
      {
         "SentenceId": 8,
         "Tokens": [
            "Ich",
            "will",
            "allerdings",
            "auch",
            "sagen",
            ":",
            "Er",
            "lässt",
            "viele",
            "Aspekte",
            ",",
            "die",
            "erwähnt",
            "werden",
            "müssten",
            ",",
            "unerwähnt",
            ",",
            "und",
            "in",
            "einigen",
            "Punkten",
            "spiegelt",
            "er",
            "die",
            "energiepolitische",
            "Realität",
            "nicht",
            "wider",
            "."
         ]
      },
      {
         "SentenceId": 9,
         "Tokens": [
            "Die",
            "vielen",
            "Innovationen",
            ",",
            "auch",
            "aus",
            "Deutschland",
            ",",
            "in",
            "den",
            "Bereichen",
            "energieeffizienter",
            "Anwendungen",
            "und",
            "Erzeugung",
            "erneuerbarer",
            "Energien",
            "werden",
            "kaum",
            "erwähnt",
            "."
         ]
      },
      {
         "SentenceId": 10,
         "Tokens": [
            "Ich",
            "glaube",
            ",",
            "Sie",
            "setzen",
            "nicht",
            "bei",
            "dem",
            "Beitrag",
            "an",
            ",",
            "den",
            "Deutschland",
            "im",
            "Bereich",
            "der",
            "Energiewende",
            "schon",
            "geleistet",
            "hat",
            "."
         ]
      },
      {
         "SentenceId": 11,
         "Tokens": [
            "Mit",
            "dem",
            "Strommarktgesetz",
            "-",
            "das",
            "ist",
            "schon",
            "erwähnt",
            "worden",
            "-",
            "und",
            "dem",
            "Energiewirtschaftsgesetz",
            "haben",
            "wir",
            "bereits",
            "festgeschrieben",
            ",",
            "dass",
            "Braunkohlekraftwerke",
            "in",
            "die",
            "Sicherheitsreserve",
            "kommen",
            "und",
            "damit",
            "vom",
            "Markt",
            "verschwinden",
            "."
         ]
      },
      {
         "SentenceId": 12,
         "Tokens": [
            "Das",
            "entspricht",
            "einem",
            "erheblichen",
            "Einsparpotenzial",
            "von",
            "über",
            "12",
            "Millionen",
            "Tonnen",
            "CO",
            "2",
            "."
         ]
      },
      {
         "SentenceId": 13,
         "Tokens": [
            "Ich",
            "will",
            "hier",
            "noch",
            "einmal",
            "sagen",
            ":",
            "Wenn",
            "man",
            "sich",
            "nur",
            "auf",
            "die",
            "Braunkohle",
            "konzentriert",
            ",",
            "zeichnet",
            "man",
            "ein",
            "falsches",
            "Bild",
            "."
         ]
      },
      {
         "SentenceId": 14,
         "Tokens": [
            "Wenn",
            "man",
            "die",
            "anderen",
            "Sektoren",
            ",",
            "die",
            "genannt",
            "worden",
            "sind",
            ",",
            "einbezieht",
            ",",
            "muss",
            "man",
            "erkennen",
            ",",
            "dass",
            "die",
            "Braunkohle",
            "der",
            "Bereich",
            "ist",
            ",",
            "der",
            "am",
            "stärksten",
            "dazu",
            "beigetragen",
            "hat",
            ",",
            "dass",
            "Deutschland",
            "diese",
            "CO",
            "2",
            "-Kurve",
            "überhaupt",
            "erreichen",
            "konnte",
            "."
         ]
      },
      {
         "SentenceId": 15,
         "Tokens": [
            "Das",
            "liegt",
            "vor",
            "allen",
            "Dingen",
            "an",
            "der",
            "Braunkohleindustrie",
            "in",
            "den",
            "ostdeutschen",
            "Ländern",
            ",",
            "die",
            "einen",
            "dementsprechenden",
            "Beitrag",
            "geleistet",
            "hat",
            "."
         ]
      },
      {
         "SentenceId": 16,
         "Tokens": [
            "In",
            "dem",
            "Antrag",
            "fehlt",
            "das",
            "Thema",
            "Strukturwandel",
            "."
         ]
      },
      {
         "SentenceId": 17,
         "Tokens": [
            "Daran",
            "merkt",
            "man",
            ",",
            "dass",
            "den",
            "Grünen",
            "der",
            "sozialpolitische",
            "Kompass",
            "abhandengekommen",
            "ist",
            "."
         ]
      },
      {
         "SentenceId": 18,
         "Tokens": [
            "Wenn",
            "es",
            "Kompetenz",
            "in",
            "Sachen",
            "Strukturwandel",
            "gibt",
            ",",
            "dann",
            "liegt",
            "sie",
            "bei",
            "der",
            "SPD",
            "."
         ]
      },
      {
         "SentenceId": 19,
         "Tokens": [
            "Wir",
            "haben",
            "das",
            "nicht",
            "nur",
            "bei",
            "dem",
            "Strukturwandel",
            "im",
            "Steinkohlenbergbau",
            "bewiesen",
            ",",
            "sondern",
            "auch",
            "in",
            "vielen",
            "anderen",
            "Branchen",
            "."
         ]
      },
      {
         "SentenceId": 20,
         "Tokens": [
            "Das",
            "heißt",
            ",",
            "Verantwortung",
            "zu",
            "tragen",
            "für",
            "die",
            "Region",
            ",",
            "für",
            "die",
            "vielen",
            "Menschen",
            ",",
            "für",
            "die",
            "Kumpels",
            ",",
            "die",
            "dort",
            "ihren",
            "Arbeitsplatz",
            "haben",
            "."
         ]
      },
      {
         "SentenceId": 21,
         "Tokens": [
            "Das",
            "muss",
            "mitgedacht",
            "werden",
            "."
         ]
      },
      {
         "SentenceId": 22,
         "Tokens": [
            "Das",
            "können",
            "Sie",
            "ja",
            "reklamieren",
            ",",
            "aber",
            "das",
            "ist",
            "zumindest",
            "nicht",
            "in",
            "Ihrem",
            "Antrag",
            "beschrieben",
            "."
         ]
      },
      {
         "SentenceId": 23,
         "Tokens": [
            "Deshalb",
            "ist",
            "Nachhaltigkeit",
            "immer",
            "eine",
            "Säule",
            "von",
            "sozialen",
            ",",
            "ökologischen",
            "und",
            "wirtschaftlichen",
            "Aspekten",
            "."
         ]
      },
      {
         "SentenceId": 24,
         "Tokens": [
            "Dies",
            "fehlt",
            "in",
            "diesem",
            "Antrag",
            "völlig",
            "."
         ]
      },
      {
         "SentenceId": 25,
         "Tokens": [
            "Es",
            "ist",
            "schon",
            "darauf",
            "hingewiesen",
            "worden",
            ",",
            "dass",
            "wir",
            "mit",
            "dem",
            "Klimaschutzplan",
            "die",
            "Kommission",
            "„",
            "Wachstum",
            ",",
            "Strukturwandel",
            "und",
            "Regionalentwicklung",
            "“",
            "ins",
            "Leben",
            "gerufen",
            "haben",
            "."
         ]
      },
      {
         "SentenceId": 26,
         "Tokens": [
            "Ich",
            "finde",
            ",",
            "es",
            "ist",
            "eine",
            "kluge",
            "Idee",
            ",",
            "Akteure",
            "an",
            "einen",
            "Tisch",
            "zu",
            "holen",
            "und",
            "zu",
            "beraten",
            ",",
            "wie",
            "der",
            "weitere",
            "Weg",
            "gestaltet",
            "werden",
            "kann",
            "."
         ]
      },
      {
         "SentenceId": 27,
         "Tokens": [
            "Dies",
            "ist",
            "aber",
            "keine",
            "Kommission",
            ",",
            "die",
            "sich",
            "mit",
            "der",
            "Überschrift",
            "„",
            "Kohleausstieg",
            "“",
            "befasst",
            ","
         ]
      },
      {
         "SentenceId": 28,
         "Tokens": [
            "sondern",
            "hier",
            "geht",
            "es",
            "darum",
            ",",
            "Aspekte",
            "aufzuzeigen",
            ",",
            "um",
            "im",
            "Konsens",
            "einen",
            "klaren",
            "Pfad",
            "aufzuzeigen",
            ",",
            "wie",
            "der",
            "Strukturwandel",
            "erfolgreich",
            "gestaltet",
            "werden",
            "kann",
            "."
         ]
      },
      {
         "SentenceId": 29,
         "Tokens": [
            "Ich",
            "möchte",
            "einen",
            "letzten",
            "Aspekt",
            "ansprechen",
            ",",
            "weil",
            "die",
            "Grünen",
            "in",
            "ihrem",
            "Antrag",
            "die",
            "Globale",
            "Allianz",
            "für",
            "den",
            "Kohleausstieg",
            "erwähnt",
            "haben",
            "."
         ]
      },
      {
         "SentenceId": 30,
         "Tokens": [
            "Ich",
            "glaube",
            ",",
            "dass",
            "die",
            "Länder",
            ",",
            "die",
            "dort",
            "erwähnt",
            "worden",
            "sind",
            ",",
            "die",
            "auf",
            "Kernenergie",
            "setzen",
            ","
         ]
      },
      {
         "SentenceId": 31,
         "Tokens": [
            "die",
            "bei",
            "der",
            "Erdgasförderung",
            "eine",
            "Fracking-Technologie",
            "anwenden",
            ",",
            "die",
            "wir",
            "hier",
            "in",
            "Deutschland",
            "in",
            "der",
            "Form",
            "nicht",
            "akzeptieren",
            ",",
            "sicherlich",
            "nicht",
            "beispielgebend",
            "für",
            "den",
            "Weg",
            "der",
            "Energiewende",
            "in",
            "Deutschland",
            "sein",
            "können",
            "."
         ]
      },
      {
         "SentenceId": 32,
         "Tokens": [
            "Von",
            "daher",
            "freue",
            "ich",
            "mich",
            "auf",
            "die",
            "lebhafte",
            "Debatte",
            ",",
            "die",
            "wir",
            "über",
            "die",
            "Energiewende",
            "noch",
            "führen",
            "werden",
            "."
         ]
      },
      {
         "SentenceId": 33,
         "Tokens": [
            "Wir",
            "sind",
            "uns",
            "der",
            "Verantwortung",
            "bewusst",
            "."
         ]
      },
      {
         "SentenceId": 34,
         "Tokens": [
            "Ich",
            "denke",
            ",",
            "auch",
            "die",
            "Kohle",
            "wird",
            "zukünftig",
            "ihren",
            "Beitrag",
            "leisten",
            "müssen",
            ",",
            "um",
            "die",
            "Energiewende",
            "so",
            "zu",
            "gestalten",
            ",",
            "dass",
            "wir",
            "international",
            "Nachahmer",
            "dafür",
            "finden",
            "."
         ]
      },
      {
         "SentenceId": 35,
         "Tokens": [
            "Vielen",
            "Dank",
            "."
         ]
      },
      {
         "SentenceId": 36,
         "Tokens": [
            "Vielen",
            "Dank",
            ",",
            "Kollege",
            "Westphal",
            "."
         ]
      },
      {
         "SentenceId": 37,
         "Tokens": [
            "-",
            "Damit",
            "schließe",
            "ich",
            "die",
            "Debatte",
            "."
         ]
      },
      {
         "SentenceId": 38,
         "Tokens": [
            "Interfraktionell",
            "wird",
            "Überweisung",
            "der",
            "Vorlage",
            "auf",
            "Drucksache",
            "19",
            "/",
            "83",
            "an",
            "den",
            "Hauptausschuss",
            "vorgeschlagen",
            "."
         ]
      },
      {
         "SentenceId": 39,
         "Tokens": [
            "Sind",
            "Sie",
            "damit",
            "einverstanden",
            "?"
         ]
      },
      {
         "SentenceId": 40,
         "Tokens": [
            "-",
            "Das",
            "ist",
            "der",
            "Fall",
            "."
         ]
      },
      {
         "SentenceId": 41,
         "Tokens": [
            "Dann",
            "ist",
            "die",
            "Überweisung",
            "so",
            "beschlossen",
            "."
         ]
      }
   ],
   "Annotations": [
      {
         "Addr": [],
         "Evidence": [],
         "Medium": [],
         "Message": [
            "2:9",
            "2:10",
            "2:1",
            "2:2",
            "2:3",
            "2:4"
         ],
         "Source": [
            "2:7"
         ],
         "Topic": [],
         "Cue": [
            "2:6"
         ],
         "PTC": []
      },
      {
         "Addr": [],
         "Evidence": [],
         "Medium": [],
         "Message": [],
         "Source": [],
         "Topic": [],
         "Cue": [
            "3:3"
         ],
         "PTC": []
      },
      {
         "Addr": [],
         "Evidence": [],
         "Medium": [],
         "Message": [],
         "Source": [],
         "Topic": [],
         "Cue": [
            "4:4"
         ],
         "PTC": []
      },
      {
         "Addr": [],
         "Evidence": [],
         "Medium": [],
         "Message": [
            "4:8"
         ],
         "Source": [
            "4:7"
         ],
         "Topic": [],
         "Cue": [
            "4:11"
         ],
         "PTC": []
      },
      {
         "Addr": [],
         "Evidence": [],
         "Medium": [],
         "Message": [
            "5:3",
            "5:4",
            "5:5",
            "5:6",
            "5:7",
            "5:8",
            "5:9",
            "5:10",
            "5:11",
            "5:12",
            "5:13",
            "5:14",
            "5:15",
            "5:16",
            "5:17",
            "5:18",
            "5:19",
            "5:20",
            "5:21",
            "5:22",
            "5:23",
            "5:24"
         ],
         "Source": [
            "5:0"
         ],
         "Topic": [],
         "Cue": [
            "5:1"
         ],
         "PTC": []
      },
      {
         "Addr": [],
         "Evidence": [],
         "Medium": [],
         "Message": [],
         "Source": [],
         "Topic": [
            "5:7"
         ],
         "Cue": [
            "5:9"
         ],
         "PTC": []
      },
      {
         "Addr": [],
         "Evidence": [],
         "Medium": [],
         "Message": [],
         "Source": [
            "5:14"
         ],
         "Topic": [
            "5:20",
            "5:21",
            "5:22",
            "5:23"
         ],
         "Cue": [
            "5:24",
            "5:19"
         ],
         "PTC": []
      },
      {
         "Addr": [],
         "Evidence": [],
         "Medium": [],
         "Message": [],
         "Source": [],
         "Topic": [],
         "Cue": [
            "7:1"
         ],
         "PTC": []
      },
      {
         "Addr": [],
         "Evidence": [],
         "Medium": [],
         "Message": [
            "8:6",
            "8:7",
            "8:8",
            "8:9",
            "8:10",
            "8:11",
            "8:12",
            "8:13",
            "8:14",
            "8:15",
            "8:16",
            "8:17",
            "8:18",
            "8:19",
            "8:20",
            "8:21",
            "8:22",
            "8:23",
            "8:24",
            "8:25",
            "8:26",
            "8:27",
            "8:28"
         ],
         "Source": [
            "8:0"
         ],
         "Topic": [],
         "Cue": [
            "8:4"
         ],
         "PTC": []
      },
      {
         "Addr": [],
         "Evidence": [],
         "Medium": [],
         "Message": [
            "8:11"
         ],
         "Source": [],
         "Topic": [],
         "Cue": [
            "8:12"
         ],
         "PTC": []
      },
      {
         "Addr": [],
         "Evidence": [],
         "Medium": [],
         "Message": [
            "9:0",
            "9:1",
            "9:2",
            "9:3",
            "9:4",
            "9:5",
            "9:6",
            "9:7",
            "9:8",
            "9:9",
            "9:10",
            "9:11",
            "9:12",
            "9:13",
            "9:14",
            "9:15",
            "9:16"
         ],
         "Source": [],
         "Topic": [],
         "Cue": [
            "9:19"
         ],
         "PTC": []
      },
      {
         "Addr": [],
         "Evidence": [],
         "Medium": [],
         "Message": [
            "10:3",
            "10:4",
            "10:5",
            "10:6",
            "10:7",
            "10:8",
            "10:9",
            "10:10",
            "10:11",
            "10:12",
            "10:13",
            "10:14",
            "10:15",
            "10:16",
            "10:17",
            "10:18",
            "10:19"
         ],
         "Source": [
            "10:0"
         ],
         "Topic": [],
         "Cue": [
            "10:1"
         ],
         "PTC": []
      },
      {
         "Addr": [],
         "Evidence": [],
         "Medium": [],
         "Message": [
            "11:4"
         ],
         "Source": [],
         "Topic": [],
         "Cue": [
            "11:7"
         ],
         "PTC": []
      },
      {
         "Addr": [],
         "Evidence": [],
         "Medium": [
            "11:10",
            "11:11",
            "11:12",
            "11:0",
            "11:1",
            "11:2"
         ],
         "Message": [
            "11:18",
            "11:19",
            "11:20",
            "11:21",
            "11:22",
            "11:23",
            "11:24",
            "11:25",
            "11:26",
            "11:27",
            "11:28"
         ],
         "Source": [
            "11:14"
         ],
         "Topic": [],
         "Cue": [
            "11:16"
         ],
         "PTC": []
      },
      {
         "Addr": [],
         "Evidence": [],
         "Medium": [],
         "Message": [
            "13:7",
            "13:8",
            "13:9",
            "13:10",
            "13:11",
            "13:12",
            "13:13",
            "13:14",
            "13:15",
            "13:16",
            "13:17",
            "13:18",
            "13:19",
            "13:20"
         ],
         "Source": [
            "13:0"
         ],
         "Topic": [],
         "Cue": [
            "13:5"
         ],
         "PTC": []
      },
      {
         "Addr": [],
         "Evidence": [],
         "Medium": [],
         "Message": [
            "13:18",
            "13:19",
            "13:20"
         ],
         "Source": [
            "13:17"
         ],
         "Topic": [],
         "Cue": [
            "13:16"
         ],
         "PTC": []
      },
      {
         "Addr": [],
         "Evidence": [],
         "Medium": [],
         "Message": [
            "14:6"
         ],
         "Source": [],
         "Topic": [],
         "Cue": [
            "14:7"
         ],
         "PTC": []
      },
      {
         "Addr": [],
         "Evidence": [],
         "Medium": [],
         "Message": [
            "14:17",
            "14:18",
            "14:19",
            "14:20",
            "14:21",
            "14:22",
            "14:23",
            "14:24",
            "14:25",
            "14:26",
            "14:27",
            "14:28",
            "14:29",
            "14:30",
            "14:31",
            "14:32",
            "14:33",
            "14:34",
            "14:35",
            "14:36",
            "14:37",
            "14:38",
            "14:39"
         ],
         "Source": [
            "14:14"
         ],
         "Topic": [],
         "Cue": [
            "14:15"
         ],
         "PTC": []
      },
      {
         "Addr": [],
         "Evidence": [],
         "Medium": [],
         "Message": [],
         "Source": [],
         "Topic": [],
         "Cue": [
            "16:2"
         ],
         "PTC": []
      },
      {
         "Addr": [],
         "Evidence": [],
         "Medium": [],
         "Message": [
            "19:2"
         ],
         "Source": [
            "19:0"
         ],
         "Topic": [],
         "Cue": [
            "19:10"
         ],
         "PTC": []
      },
      {
         "Addr": [],
         "Evidence": [],
         "Medium": [],
         "Message": [
            "22:0"
         ],
         "Source": [
            "22:2"
         ],
         "Topic": [],
         "Cue": [
            "22:4"
         ],
         "PTC": []
      },
      {
         "Addr": [],
         "Evidence": [],
         "Medium": [],
         "Message": [],
         "Source": [
            "22:12"
         ],
         "Topic": [],
         "Cue": [
            "22:13"
         ],
         "PTC": []
      },
      {
         "Addr": [],
         "Evidence": [],
         "Medium": [
            "22:11",
            "22:12",
            "22:13"
         ],
         "Message": [],
         "Source": [],
         "Topic": [
            "22:7"
         ],
         "Cue": [
            "22:14"
         ],
         "PTC": []
      },
      {
         "Addr": [],
         "Evidence": [],
         "Medium": [],
         "Message": [],
         "Source": [],
         "Topic": [],
         "Cue": [
            "24:4"
         ],
         "PTC": []
      },
      {
         "Addr": [],
         "Evidence": [],
         "Medium": [],
         "Message": [
            "25:7",
            "25:8",
            "25:9",
            "25:10",
            "25:11",
            "25:12",
            "25:13",
            "25:14",
            "25:15",
            "25:16",
            "25:17",
            "25:18",
            "25:19",
            "25:20",
            "25:21",
            "25:22",
            "25:23",
            "25:24",
            "25:3"
         ],
         "Source": [],
         "Topic": [],
         "Cue": [
            "25:4"
         ],
         "PTC": []
      },
      {
         "Addr": [],
         "Evidence": [],
         "Medium": [],
         "Message": [
            "26:3",
            "26:4",
            "26:5",
            "26:6",
            "26:7",
            "26:8",
            "26:9",
            "26:10",
            "26:11",
            "26:12",
            "26:13",
            "26:14",
            "26:15",
            "26:16",
            "26:17",
            "26:18",
            "26:19",
            "26:20",
            "26:21",
            "26:22",
            "26:23",
            "26:24",
            "26:25"
         ],
         "Source": [
            "26:0"
         ],
         "Topic": [],
         "Cue": [
            "26:1"
         ],
         "PTC": []
      },
      {
         "Addr": [],
         "Evidence": [],
         "Medium": [],
         "Message": [
            "26:9",
            "26:10",
            "26:11",
            "26:12",
            "26:13",
            "26:14",
            "26:15",
            "26:16",
            "26:17",
            "26:18",
            "26:19",
            "26:20",
            "26:21",
            "26:22",
            "26:23",
            "26:24",
            "26:25"
         ],
         "Source": [],
         "Topic": [],
         "Cue": [
            "26:7"
         ],
         "PTC": []
      },
      {
         "Addr": [],
         "Evidence": [],
         "Medium": [],
         "Message": [],
         "Source": [],
         "Topic": [
            "26:19",
            "26:20",
            "26:21",
            "26:22",
            "26:23",
            "26:24",
            "26:25"
         ],
         "Cue": [
            "26:17"
         ],
         "PTC": []
      },
      {
         "Addr": [],
         "Evidence": [],
         "Medium": [],
         "Message": [],
         "Source": [],
         "Topic": [],
         "Cue": [
            "28:7",
            "28:6"
         ],
         "PTC": []
      },
      {
         "Addr": [],
         "Evidence": [],
         "Medium": [],
         "Message": [
            "28:12",
            "28:13",
            "28:14",
            "28:17",
            "28:18",
            "28:19",
            "28:20",
            "28:21",
            "28:22",
            "28:23"
         ],
         "Source": [],
         "Topic": [],
         "Cue": [
            "28:15"
         ],
         "PTC": []
      },
      {
         "Addr": [],
         "Evidence": [],
         "Medium": [],
         "Message": [],
         "Source": [
            "29:0"
         ],
         "Topic": [
            "29:2",
            "29:3",
            "29:4"
         ],
         "Cue": [
            "29:5"
         ],
         "PTC": []
      },
      {
         "Addr": [],
         "Evidence": [],
         "Medium": [],
         "Message": [],
         "Source": [
            "29:11"
         ],
         "Topic": [],
         "Cue": [
            "29:12"
         ],
         "PTC": []
      },
      {
         "Addr": [],
         "Evidence": [],
         "Medium": [
            "29:10",
            "29:11",
            "29:12"
         ],
         "Message": [
            "29:13",
            "29:14",
            "29:15",
            "29:16",
            "29:17",
            "29:18"
         ],
         "Source": [
            "29:8",
            "29:9"
         ],
         "Topic": [],
         "Cue": [
            "29:19"
         ],
         "PTC": []
      },
      {
         "Addr": [],
         "Evidence": [],
         "Medium": [],
         "Message": [
            "30:3",
            "30:4",
            "30:5",
            "30:6",
            "30:7",
            "30:8",
            "30:9",
            "30:10",
            "30:11",
            "30:12",
            "30:13",
            "30:14",
            "30:15",
            "30:16",
            "30:17",
            "31:0",
            "31:1",
            "31:2",
            "31:3",
            "31:4",
            "31:5",
            "31:6",
            "31:7",
            "31:8",
            "31:9",
            "31:10",
            "31:11",
            "31:12",
            "31:13",
            "31:14",
            "31:15",
            "31:16",
            "31:17",
            "31:18",
            "31:19",
            "31:20",
            "31:21",
            "31:22",
            "31:23",
            "31:24",
            "31:25",
            "31:26",
            "31:27",
            "31:28",
            "31:29",
            "31:30"
         ],
         "Source": [
            "30:0"
         ],
         "Topic": [],
         "Cue": [
            "30:1"
         ],
         "PTC": []
      },
      {
         "Addr": [],
         "Evidence": [],
         "Medium": [
            "30:8"
         ],
         "Message": [
            "30:7"
         ],
         "Source": [],
         "Topic": [],
         "Cue": [
            "30:9"
         ],
         "PTC": []
      },
      {
         "Addr": [],
         "Evidence": [],
         "Medium": [],
         "Message": [
            "31:8"
         ],
         "Source": [
            "31:9"
         ],
         "Topic": [],
         "Cue": [
            "31:17"
         ],
         "PTC": []
      },
      {
         "Addr": [],
         "Evidence": [],
         "Medium": [],
         "Message": [
            "32:5",
            "32:6",
            "32:7",
            "32:8",
            "32:9",
            "32:10",
            "32:11",
            "32:12",
            "32:13",
            "32:14",
            "32:15",
            "32:16",
            "32:17"
         ],
         "Source": [
            "32:3"
         ],
         "Topic": [],
         "Cue": [
            "32:2"
         ],
         "PTC": [
            "32:4"
         ]
      },
      {
         "Addr": [],
         "Evidence": [],
         "Medium": [],
         "Message": [],
         "Source": [],
         "Topic": [],
         "Cue": [
            "32:8"
         ],
         "PTC": []
      },
      {
         "Addr": [],
         "Evidence": [],
         "Medium": [],
         "Message": [],
         "Source": [
            "32:11"
         ],
         "Topic": [
            "32:12",
            "32:13",
            "32:14"
         ],
         "Cue": [
            "32:16",
            "32:10"
         ],
         "PTC": []
      },
      {
         "Addr": [],
         "Evidence": [],
         "Medium": [],
         "Message": [
            "34:3",
            "34:4",
            "34:5",
            "34:6",
            "34:7",
            "34:8",
            "34:9",
            "34:10",
            "34:11",
            "34:12",
            "34:13",
            "34:14",
            "34:15",
            "34:16",
            "34:17",
            "34:18",
            "34:19",
            "34:20",
            "34:21",
            "34:22",
            "34:23",
            "34:24",
            "34:25"
         ],
         "Source": [
            "34:0"
         ],
         "Topic": [],
         "Cue": [
            "34:1"
         ],
         "PTC": []
      },
      {
         "Addr": [],
         "Evidence": [],
         "Medium": [],
         "Message": [],
         "Source": [],
         "Topic": [],
         "Cue": [
            "37:5"
         ],
         "PTC": []
      },
      {
         "Addr": [],
         "Evidence": [],
         "Medium": [
            "38:5",
            "38:6",
            "38:7",
            "38:8",
            "38:9"
         ],
         "Message": [],
         "Source": [],
         "Topic": [],
         "Cue": [
            "38:4"
         ],
         "PTC": []
      },
      {
         "Addr": [],
         "Evidence": [],
         "Medium": [],
         "Message": [
            "38:2",
            "38:3",
            "38:4",
            "38:5",
            "38:6",
            "38:7",
            "38:8",
            "38:9",
            "38:10",
            "38:11",
            "38:12"
         ],
         "Source": [
            "38:0"
         ],
         "Topic": [],
         "Cue": [
            "38:13"
         ],
         "PTC": []
      },
      {
         "Addr": [],
         "Evidence": [],
         "Medium": [],
         "Message": [
            "41:2",
            "41:3"
         ],
         "Source": [],
         "Topic": [],
         "Cue": [
            "41:5"
         ],
         "PTC": []
      }
   ]
}